{
    "id": 129041924,
    "name": "Piss 2",
    "author": "RustyGD25",
    "creators": [],
    "verifier": "Rusty",
    "verification": "https://www.youtube.com/watch?v=XtiKG2krJ9g",
    "percentToQualify": "100",
    "records": [
        {
             "user": "Sadisyourlife",
            "link": "https://discord.com/channels/1413625809112924307/1413628930065301616/1448096998765887700",
            "percent": 100,
            "hz": 240
        },
        {
            "user": "finni1505",
            "link": "https://youtu.be/JbWY9KlXn0U",
            "hz": "240",
            "percent": 100
        }
    ]
}
